Orange3_Educational_zh-0.5.0-py3.8-nspkg.pth
orangecontrib/educational/__init__.py
orangecontrib/educational/tests/__init__.py
orangecontrib/educational/tutorials/__init__.py
orangecontrib/educational/widgets/__init__.py
orangecontrib/educational/widgets/ow1ka.py
orangecontrib/educational/widgets/owcreatetable.py
orangecontrib/educational/widgets/owgooglesheets.py
orangecontrib/educational/widgets/owgradientdescent.py
orangecontrib/educational/widgets/owkmeans.py
orangecontrib/educational/widgets/owpiecharts.py
orangecontrib/educational/widgets/owpolynomialclassification.py
orangecontrib/educational/widgets/owpolynomialregression.py
orangecontrib/educational/widgets/owrandomdata.py
orangecontrib/educational/widgets/highcharts/__init__.py
orangecontrib/educational/widgets/highcharts/highcharts.py
orangecontrib/educational/widgets/highcharts/_highcharts/LICENSE
orangecontrib/educational/widgets/highcharts/_highcharts/chart.html
orangecontrib/educational/widgets/highcharts/_highcharts/highcharts-more.js
orangecontrib/educational/widgets/highcharts/_highcharts/highmaps.js
orangecontrib/educational/widgets/highcharts/_highcharts/highstock.js
orangecontrib/educational/widgets/highcharts/_highcharts/jquery.js
orangecontrib/educational/widgets/highcharts/_highcharts/map.js
orangecontrib/educational/widgets/highcharts/_highcharts/no-data-to-display.js
orangecontrib/educational/widgets/highcharts/_highcharts/orange-selection.js
orangecontrib/educational/widgets/highcharts/_highcharts/orange-theme.js
orangecontrib/educational/widgets/highcharts/tests/test_highcharts.py
orangecontrib/educational/widgets/icons/1ka.svg
orangecontrib/educational/widgets/icons/CreateTable.svg
orangecontrib/educational/widgets/icons/GoogleSheets.svg
orangecontrib/educational/widgets/icons/GradientDescent.svg
orangecontrib/educational/widgets/icons/InteractiveKMeans.svg
orangecontrib/educational/widgets/icons/PieChart.svg
orangecontrib/educational/widgets/icons/RandomData.svg
Orange3_Educational_zh-0.5.0.dist-info/LICENSE
Orange3_Educational_zh-0.5.0.dist-info/METADATA
Orange3_Educational_zh-0.5.0.dist-info/WHEEL
Orange3_Educational_zh-0.5.0.dist-info/entry_points.txt
Orange3_Educational_zh-0.5.0.dist-info/namespace_packages.txt
Orange3_Educational_zh-0.5.0.dist-info/top_level.txt
Orange3_Educational_zh-0.5.0.dist-info/RECORD
