Metadata-Version: 2.1
Name: Orange3-Educational-zh
Version: 0.5.0
Summary: Orange Educational add-on for Orange data mining software package.
Home-page: https://github.com/biolab/orange3-educational
Download-URL: https://github.com/biolab/orange3-educational/releases
Author: Bioinformatics Laboratory, FRI UL
Author-email: contact@orange.biolab.si
License: BSD
Keywords: orange3 add-on
Platform: UNKNOWN
License-File: LICENSE
Requires-Dist: Orange3-zh (>=3.31.1)
Requires-Dist: BeautifulSoup4
Requires-Dist: numpy
Provides-Extra: doc
Requires-Dist: sphinx ; extra == 'doc'
Requires-Dist: recommonmark ; extra == 'doc'
Requires-Dist: sphinx-rtd-theme ; extra == 'doc'
Provides-Extra: test
Requires-Dist: coverage ; extra == 'test'
